{"config":{"output_file":null,"full_docs":false,"pub_only":true,"reachable_only":true,"distro_crate":false,"signatures":false,"borrow_data":false},"version":"0.19.0","compilation":{"directory":"/home/gautam/.cargo/registry/src/github.com-1ecc6299db9ec823/blake2-0.8.1","program":"/home/gautam/.rustup/toolchains/stable-x86_64-unknown-linux-gnu/bin/rls","arguments":["--crate-name","blake2","/home/gautam/.cargo/registry/src/github.com-1ecc6299db9ec823/blake2-0.8.1/src/lib.rs","--color","never","--crate-type","lib","--emit=dep-info,metadata","-C","debuginfo=2","-C","metadata=b4391c65afd81636","-C","extra-filename=-b4391c65afd81636","--out-dir","/home/gautam/code/substrate-tcr/target/rls/debug/deps","-L","dependency=/home/gautam/code/substrate-tcr/target/rls/debug/deps","--extern","byte_tools=/home/gautam/code/substrate-tcr/target/rls/debug/deps/libbyte_tools-7b2c9c4c48ef375e.rmeta","--extern","crypto_mac=/home/gautam/code/substrate-tcr/target/rls/debug/deps/libcrypto_mac-e6fa89a5f5bede4b.rmeta","--extern","digest=/home/gautam/code/substrate-tcr/target/rls/debug/deps/libdigest-23f67715f96a4c54.rmeta","--extern","opaque_debug=/home/gautam/code/substrate-tcr/target/rls/debug/deps/libopaque_debug-6c26da520a2470da.rmeta","--cap-lints","allow","--error-format=json","--sysroot","/home/gautam/.rustup/toolchains/stable-x86_64-unknown-linux-gnu"],"output":"/home/gautam/code/substrate-tcr/target/rls/debug/deps/libblake2-b4391c65afd81636.rmeta"},"prelude":{"crate_id":{"name":"blake2","disambiguator":[17564809680265979474,11440811936911889581]},"crate_root":"/home/gautam/.cargo/registry/src/github.com-1ecc6299db9ec823/blake2-0.8.1/src","external_crates":[{"file_name":"/home/gautam/.cargo/registry/src/github.com-1ecc6299db9ec823/blake2-0.8.1/src/lib.rs","num":1,"id":{"name":"core","disambiguator":[9113878364975505769,4626460723841361367]}},{"file_name":"/home/gautam/.cargo/registry/src/github.com-1ecc6299db9ec823/blake2-0.8.1/src/lib.rs","num":2,"id":{"name":"compiler_builtins","disambiguator":[10636203250160794641,6979396832464280682]}},{"file_name":"/home/gautam/.cargo/registry/src/github.com-1ecc6299db9ec823/blake2-0.8.1/src/lib.rs","num":3,"id":{"name":"rustc_std_workspace_core","disambiguator":[7259142600435629501,12221323364939802703]}},{"file_name":"/home/gautam/.cargo/registry/src/github.com-1ecc6299db9ec823/blake2-0.8.1/src/lib.rs","num":4,"id":{"name":"opaque_debug","disambiguator":[4066210372712447704,12959402483192229152]}},{"file_name":"/home/gautam/.cargo/registry/src/github.com-1ecc6299db9ec823/blake2-0.8.1/src/lib.rs","num":5,"id":{"name":"digest","disambiguator":[10177543274840385639,2242018114672693210]}},{"file_name":"/home/gautam/.cargo/registry/src/github.com-1ecc6299db9ec823/blake2-0.8.1/src/lib.rs","num":6,"id":{"name":"generic_array","disambiguator":[14550314689580146068,6678877153218097606]}},{"file_name":"/home/gautam/.cargo/registry/src/github.com-1ecc6299db9ec823/blake2-0.8.1/src/lib.rs","num":7,"id":{"name":"typenum","disambiguator":[12989350392175717619,11979469666288565117]}},{"file_name":"/home/gautam/.cargo/registry/src/github.com-1ecc6299db9ec823/blake2-0.8.1/src/lib.rs","num":8,"id":{"name":"std","disambiguator":[4418738106075590160,6298063093324017560]}},{"file_name":"/home/gautam/.cargo/registry/src/github.com-1ecc6299db9ec823/blake2-0.8.1/src/lib.rs","num":9,"id":{"name":"alloc","disambiguator":[245280942947536957,12219005383890086938]}},{"file_name":"/home/gautam/.cargo/registry/src/github.com-1ecc6299db9ec823/blake2-0.8.1/src/lib.rs","num":10,"id":{"name":"libc","disambiguator":[6161946279237914842,16521306710208745576]}},{"file_name":"/home/gautam/.cargo/registry/src/github.com-1ecc6299db9ec823/blake2-0.8.1/src/lib.rs","num":11,"id":{"name":"unwind","disambiguator":[6542909105960794691,9677219093962929367]}},{"file_name":"/home/gautam/.cargo/registry/src/github.com-1ecc6299db9ec823/blake2-0.8.1/src/lib.rs","num":12,"id":{"name":"cfg_if","disambiguator":[5468829561226316808,7834745881253856659]}},{"file_name":"/home/gautam/.cargo/registry/src/github.com-1ecc6299db9ec823/blake2-0.8.1/src/lib.rs","num":13,"id":{"name":"hashbrown","disambiguator":[17700629721805382410,8884445337419759755]}},{"file_name":"/home/gautam/.cargo/registry/src/github.com-1ecc6299db9ec823/blake2-0.8.1/src/lib.rs","num":14,"id":{"name":"rustc_std_workspace_alloc","disambiguator":[5673318663856259921,7992701887106127366]}},{"file_name":"/home/gautam/.cargo/registry/src/github.com-1ecc6299db9ec823/blake2-0.8.1/src/lib.rs","num":15,"id":{"name":"backtrace","disambiguator":[14096840682646779984,4894716104918169263]}},{"file_name":"/home/gautam/.cargo/registry/src/github.com-1ecc6299db9ec823/blake2-0.8.1/src/lib.rs","num":16,"id":{"name":"rustc_demangle","disambiguator":[17167590092810160364,15681868143498786567]}},{"file_name":"/home/gautam/.cargo/registry/src/github.com-1ecc6299db9ec823/blake2-0.8.1/src/lib.rs","num":17,"id":{"name":"backtrace_sys","disambiguator":[9809686796458150241,12960706147778414440]}},{"file_name":"/home/gautam/.cargo/registry/src/github.com-1ecc6299db9ec823/blake2-0.8.1/src/lib.rs","num":18,"id":{"name":"panic_unwind","disambiguator":[14218938340851961837,11099897245983054425]}},{"file_name":"/home/gautam/.cargo/registry/src/github.com-1ecc6299db9ec823/blake2-0.8.1/src/lib.rs","num":19,"id":{"name":"byte_tools","disambiguator":[13284303416580267306,6672964497037622010]}},{"file_name":"/home/gautam/.cargo/registry/src/github.com-1ecc6299db9ec823/blake2-0.8.1/src/lib.rs","num":20,"id":{"name":"crypto_mac","disambiguator":[17662922819611798760,610220481490235648]}},{"file_name":"/home/gautam/.cargo/registry/src/github.com-1ecc6299db9ec823/blake2-0.8.1/src/lib.rs","num":21,"id":{"name":"subtle","disambiguator":[7464567191336452347,17239592767782378322]}}],"span":{"file_name":"/home/gautam/.cargo/registry/src/github.com-1ecc6299db9ec823/blake2-0.8.1/src/lib.rs","byte_start":0,"byte_end":3376,"line_start":1,"line_end":116,"column_start":1,"column_end":40}},"imports":[{"kind":"Use","ref_id":{"krate":5,"index":28},"span":{"file_name":"/home/gautam/.cargo/registry/src/github.com-1ecc6299db9ec823/blake2-0.8.1/src/lib.rs","byte_start":3289,"byte_end":3295,"line_start":114,"line_end":114,"column_start":17,"column_end":23},"alias_span":null,"name":"Digest","value":"","parent":{"krate":0,"index":0}},{"kind":"Use","ref_id":{"krate":0,"index":380},"span":{"file_name":"/home/gautam/.cargo/registry/src/github.com-1ecc6299db9ec823/blake2-0.8.1/src/lib.rs","byte_start":3315,"byte_end":3322,"line_start":115,"line_end":115,"column_start":19,"column_end":26},"alias_span":null,"name":"Blake2b","value":"","parent":{"krate":0,"index":0}},{"kind":"Use","ref_id":{"krate":0,"index":364},"span":{"file_name":"/home/gautam/.cargo/registry/src/github.com-1ecc6299db9ec823/blake2-0.8.1/src/lib.rs","byte_start":3324,"byte_end":3334,"line_start":115,"line_end":115,"column_start":28,"column_end":38},"alias_span":null,"name":"VarBlake2b","value":"","parent":{"krate":0,"index":0}},{"kind":"Use","ref_id":{"krate":0,"index":483},"span":{"file_name":"/home/gautam/.cargo/registry/src/github.com-1ecc6299db9ec823/blake2-0.8.1/src/lib.rs","byte_start":3355,"byte_end":3362,"line_start":116,"line_end":116,"column_start":19,"column_end":26},"alias_span":null,"name":"Blake2s","value":"","parent":{"krate":0,"index":0}},{"kind":"Use","ref_id":{"krate":0,"index":467},"span":{"file_name":"/home/gautam/.cargo/registry/src/github.com-1ecc6299db9ec823/blake2-0.8.1/src/lib.rs","byte_start":3364,"byte_end":3374,"line_start":116,"line_end":116,"column_start":28,"column_end":38},"alias_span":null,"name":"VarBlake2s","value":"","parent":{"krate":0,"index":0}}],"defs":[{"kind":"Mod","id":{"krate":0,"index":0},"span":{"file_name":"/home/gautam/.cargo/registry/src/github.com-1ecc6299db9ec823/blake2-0.8.1/src/lib.rs","byte_start":0,"byte_end":3376,"line_start":1,"line_end":116,"column_start":1,"column_end":40},"name":"","qualname":"::","value":"/home/gautam/.cargo/registry/src/github.com-1ecc6299db9ec823/blake2-0.8.1/src/lib.rs","parent":null,"children":[{"krate":0,"index":10},{"krate":0,"index":11},{"krate":0,"index":12},{"krate":0,"index":13},{"krate":0,"index":14},{"krate":0,"index":15},{"krate":0,"index":16},{"krate":0,"index":17},{"krate":0,"index":25},{"krate":0,"index":44},{"krate":0,"index":99},{"krate":0,"index":101},{"krate":0,"index":106},{"krate":0,"index":111},{"krate":0,"index":112},{"krate":0,"index":115}],"decl_id":null,"docs":" An implementation of the [BLAKE2][1] hash functions.","sig":null,"attributes":[{"value":"no_std","span":{"file_name":"/home/gautam/.cargo/registry/src/github.com-1ecc6299db9ec823/blake2-0.8.1/src/lib.rs","byte_start":2745,"byte_end":2755,"line_start":86,"line_end":86,"column_start":1,"column_end":11}},{"value":"warn(missing_docs)","span":{"file_name":"/home/gautam/.cargo/registry/src/github.com-1ecc6299db9ec823/blake2-0.8.1/src/lib.rs","byte_start":2859,"byte_end":2881,"line_start":89,"line_end":89,"column_start":1,"column_end":23}}]},{"kind":"Struct","id":{"krate":0,"index":364},"span":{"file_name":"/home/gautam/.cargo/registry/src/github.com-1ecc6299db9ec823/blake2-0.8.1/src/blake2b.rs","byte_start":29076,"byte_end":29086,"line_start":4,"line_end":4,"column_start":14,"column_end":24},"name":"VarBlake2b","qualname":"::blake2b::VarBlake2b","value":"VarBlake2b {  }","parent":null,"children":[{"krate":0,"index":365},{"krate":0,"index":367},{"krate":0,"index":369},{"krate":0,"index":370},{"krate":0,"index":371},{"krate":0,"index":373},{"krate":0,"index":375}],"decl_id":null,"docs":"Blake2b instance with a variable output.\n","sig":null,"attributes":[]},{"kind":"Struct","id":{"krate":0,"index":380},"span":{"file_name":"/home/gautam/.cargo/registry/src/github.com-1ecc6299db9ec823/blake2-0.8.1/src/blake2b.rs","byte_start":29088,"byte_end":29095,"line_start":4,"line_end":4,"column_start":26,"column_end":33},"name":"Blake2b","qualname":"::blake2b::Blake2b","value":"Blake2b {  }","parent":null,"children":[{"krate":0,"index":381}],"decl_id":null,"docs":"Blake2b instance with a fixed output.\n","sig":null,"attributes":[]},{"kind":"Struct","id":{"krate":0,"index":467},"span":{"file_name":"/home/gautam/.cargo/registry/src/github.com-1ecc6299db9ec823/blake2-0.8.1/src/blake2s.rs","byte_start":29335,"byte_end":29345,"line_start":4,"line_end":4,"column_start":14,"column_end":24},"name":"VarBlake2s","qualname":"::blake2s::VarBlake2s","value":"VarBlake2s {  }","parent":null,"children":[{"krate":0,"index":468},{"krate":0,"index":470},{"krate":0,"index":472},{"krate":0,"index":473},{"krate":0,"index":474},{"krate":0,"index":476},{"krate":0,"index":478}],"decl_id":null,"docs":"Blake2s instance with a variable output.\n","sig":null,"attributes":[]},{"kind":"Struct","id":{"krate":0,"index":483},"span":{"file_name":"/home/gautam/.cargo/registry/src/github.com-1ecc6299db9ec823/blake2-0.8.1/src/blake2s.rs","byte_start":29347,"byte_end":29354,"line_start":4,"line_end":4,"column_start":26,"column_end":33},"name":"Blake2s","qualname":"::blake2s::Blake2s","value":"Blake2s {  }","parent":null,"children":[{"krate":0,"index":484}],"decl_id":null,"docs":"Blake2s instance with a fixed output.\n","sig":null,"attributes":[]}],"impls":[{"id":8,"kind":"Inherent","span":{"file_name":"/home/gautam/.cargo/registry/src/github.com-1ecc6299db9ec823/blake2-0.8.1/src/simd/simdty.rs","byte_start":12339,"byte_end":12344,"line_start":69,"line_end":69,"column_start":9,"column_end":14},"value":"","parent":null,"children":[{"krate":0,"index":58}],"docs":"","sig":null,"attributes":[]},{"id":9,"kind":"Direct","span":{"file_name":"/home/gautam/.cargo/registry/src/github.com-1ecc6299db9ec823/blake2-0.8.1/src/simd/simdty.rs","byte_start":12498,"byte_end":12503,"line_start":76,"line_end":76,"column_start":31,"column_end":36},"value":"","parent":null,"children":[],"docs":"","sig":null,"attributes":[]},{"id":10,"kind":"Direct","span":{"file_name":"/home/gautam/.cargo/registry/src/github.com-1ecc6299db9ec823/blake2-0.8.1/src/simd/simdty.rs","byte_start":12540,"byte_end":12545,"line_start":77,"line_end":77,"column_start":31,"column_end":36},"value":"","parent":null,"children":[],"docs":"","sig":null,"attributes":[]},{"id":11,"kind":"Direct","span":{"file_name":"/home/gautam/.cargo/registry/src/github.com-1ecc6299db9ec823/blake2-0.8.1/src/simd/simdty.rs","byte_start":12582,"byte_end":12587,"line_start":78,"line_end":78,"column_start":31,"column_end":36},"value":"","parent":null,"children":[],"docs":"","sig":null,"attributes":[]},{"id":12,"kind":"Direct","span":{"file_name":"/home/gautam/.cargo/registry/src/github.com-1ecc6299db9ec823/blake2-0.8.1/src/simd/simdty.rs","byte_start":12624,"byte_end":12630,"line_start":79,"line_end":79,"column_start":31,"column_end":37},"value":"","parent":null,"children":[],"docs":"","sig":null,"attributes":[]},{"id":13,"kind":"Direct","span":{"file_name":"/home/gautam/.cargo/registry/src/github.com-1ecc6299db9ec823/blake2-0.8.1/src/simd/simdty.rs","byte_start":12667,"byte_end":12673,"line_start":80,"line_end":80,"column_start":31,"column_end":37},"value":"","parent":null,"children":[],"docs":"","sig":null,"attributes":[]}],"refs":[],"macro_refs":[],"relations":[{"span":{"file_name":"/home/gautam/.cargo/registry/src/github.com-1ecc6299db9ec823/blake2-0.8.1/src/simd/simdty.rs","byte_start":12339,"byte_end":12344,"line_start":69,"line_end":69,"column_start":9,"column_end":14},"kind":{"Impl":{"id":8}},"from":{"krate":0,"index":131},"to":{"krate":4294967295,"index":4294967295}},{"span":{"file_name":"/home/gautam/.cargo/registry/src/github.com-1ecc6299db9ec823/blake2-0.8.1/src/simd/simdty.rs","byte_start":12498,"byte_end":12503,"line_start":76,"line_end":76,"column_start":31,"column_end":36},"kind":{"Impl":{"id":9}},"from":{"krate":0,"index":118},"to":{"krate":0,"index":28}},{"span":{"file_name":"/home/gautam/.cargo/registry/src/github.com-1ecc6299db9ec823/blake2-0.8.1/src/simd/simdty.rs","byte_start":12540,"byte_end":12545,"line_start":77,"line_end":77,"column_start":31,"column_end":36},"kind":{"Impl":{"id":10}},"from":{"krate":0,"index":131},"to":{"krate":0,"index":28}},{"span":{"file_name":"/home/gautam/.cargo/registry/src/github.com-1ecc6299db9ec823/blake2-0.8.1/src/simd/simdty.rs","byte_start":12582,"byte_end":12587,"line_start":78,"line_end":78,"column_start":31,"column_end":36},"kind":{"Impl":{"id":11}},"from":{"krate":0,"index":146},"to":{"krate":0,"index":28}},{"span":{"file_name":"/home/gautam/.cargo/registry/src/github.com-1ecc6299db9ec823/blake2-0.8.1/src/simd/simdty.rs","byte_start":12624,"byte_end":12630,"line_start":79,"line_end":79,"column_start":31,"column_end":37},"kind":{"Impl":{"id":12}},"from":{"krate":0,"index":165},"to":{"krate":0,"index":28}},{"span":{"file_name":"/home/gautam/.cargo/registry/src/github.com-1ecc6299db9ec823/blake2-0.8.1/src/simd/simdty.rs","byte_start":12667,"byte_end":12673,"line_start":80,"line_end":80,"column_start":31,"column_end":37},"kind":{"Impl":{"id":13}},"from":{"krate":0,"index":192},"to":{"krate":0,"index":28}},{"span":{"file_name":"/home/gautam/.cargo/registry/src/github.com-1ecc6299db9ec823/blake2-0.8.1/src/simd/mod.rs","byte_start":6869,"byte_end":6873,"line_start":17,"line_end":17,"column_start":23,"column_end":27},"kind":"SuperTrait","from":{"krate":1,"index":1543},"to":{"krate":0,"index":85}}]}