{"config":{"output_file":null,"full_docs":false,"pub_only":true,"reachable_only":true,"distro_crate":false,"signatures":false,"borrow_data":false},"version":"0.19.0","compilation":{"directory":"/home/gautam/.cargo/registry/src/github.com-1ecc6299db9ec823/proc-macro-crate-0.1.4","program":"/home/gautam/.rustup/toolchains/stable-x86_64-unknown-linux-gnu/bin/rls","arguments":["--edition=2018","--crate-name","proc_macro_crate","/home/gautam/.cargo/registry/src/github.com-1ecc6299db9ec823/proc-macro-crate-0.1.4/src/lib.rs","--json=diagnostic-rendered-ansi,artifacts","--crate-type","lib","--emit=dep-info,metadata,link","-C","debuginfo=2","-C","metadata=1e45fa62262e2ea3","-C","extra-filename=-1e45fa62262e2ea3","--out-dir","/home/gautam/code/substrate-tcr/target/rls/debug/deps","-L","dependency=/home/gautam/code/substrate-tcr/target/rls/debug/deps","--extern","toml=/home/gautam/code/substrate-tcr/target/rls/debug/deps/libtoml-e492271205976f2c.rmeta","--cap-lints","allow","--error-format=json","--sysroot","/home/gautam/.rustup/toolchains/stable-x86_64-unknown-linux-gnu"],"output":"/home/gautam/code/substrate-tcr/target/rls/debug/deps/libproc_macro_crate-1e45fa62262e2ea3.rmeta"},"prelude":{"crate_id":{"name":"proc_macro_crate","disambiguator":[5794593589027904336,6100086748149860120]},"crate_root":"/home/gautam/.cargo/registry/src/github.com-1ecc6299db9ec823/proc-macro-crate-0.1.4/src","external_crates":[{"file_name":"/home/gautam/.cargo/registry/src/github.com-1ecc6299db9ec823/proc-macro-crate-0.1.4/src/lib.rs","num":1,"id":{"name":"std","disambiguator":[4418738106075590160,6298063093324017560]}},{"file_name":"/home/gautam/.cargo/registry/src/github.com-1ecc6299db9ec823/proc-macro-crate-0.1.4/src/lib.rs","num":2,"id":{"name":"core","disambiguator":[9113878364975505769,4626460723841361367]}},{"file_name":"/home/gautam/.cargo/registry/src/github.com-1ecc6299db9ec823/proc-macro-crate-0.1.4/src/lib.rs","num":3,"id":{"name":"compiler_builtins","disambiguator":[10636203250160794641,6979396832464280682]}},{"file_name":"/home/gautam/.cargo/registry/src/github.com-1ecc6299db9ec823/proc-macro-crate-0.1.4/src/lib.rs","num":4,"id":{"name":"rustc_std_workspace_core","disambiguator":[7259142600435629501,12221323364939802703]}},{"file_name":"/home/gautam/.cargo/registry/src/github.com-1ecc6299db9ec823/proc-macro-crate-0.1.4/src/lib.rs","num":5,"id":{"name":"alloc","disambiguator":[245280942947536957,12219005383890086938]}},{"file_name":"/home/gautam/.cargo/registry/src/github.com-1ecc6299db9ec823/proc-macro-crate-0.1.4/src/lib.rs","num":6,"id":{"name":"libc","disambiguator":[6161946279237914842,16521306710208745576]}},{"file_name":"/home/gautam/.cargo/registry/src/github.com-1ecc6299db9ec823/proc-macro-crate-0.1.4/src/lib.rs","num":7,"id":{"name":"unwind","disambiguator":[6542909105960794691,9677219093962929367]}},{"file_name":"/home/gautam/.cargo/registry/src/github.com-1ecc6299db9ec823/proc-macro-crate-0.1.4/src/lib.rs","num":8,"id":{"name":"cfg_if","disambiguator":[5468829561226316808,7834745881253856659]}},{"file_name":"/home/gautam/.cargo/registry/src/github.com-1ecc6299db9ec823/proc-macro-crate-0.1.4/src/lib.rs","num":9,"id":{"name":"hashbrown","disambiguator":[17700629721805382410,8884445337419759755]}},{"file_name":"/home/gautam/.cargo/registry/src/github.com-1ecc6299db9ec823/proc-macro-crate-0.1.4/src/lib.rs","num":10,"id":{"name":"rustc_std_workspace_alloc","disambiguator":[5673318663856259921,7992701887106127366]}},{"file_name":"/home/gautam/.cargo/registry/src/github.com-1ecc6299db9ec823/proc-macro-crate-0.1.4/src/lib.rs","num":11,"id":{"name":"backtrace","disambiguator":[14096840682646779984,4894716104918169263]}},{"file_name":"/home/gautam/.cargo/registry/src/github.com-1ecc6299db9ec823/proc-macro-crate-0.1.4/src/lib.rs","num":12,"id":{"name":"rustc_demangle","disambiguator":[17167590092810160364,15681868143498786567]}},{"file_name":"/home/gautam/.cargo/registry/src/github.com-1ecc6299db9ec823/proc-macro-crate-0.1.4/src/lib.rs","num":13,"id":{"name":"backtrace_sys","disambiguator":[9809686796458150241,12960706147778414440]}},{"file_name":"/home/gautam/.cargo/registry/src/github.com-1ecc6299db9ec823/proc-macro-crate-0.1.4/src/lib.rs","num":14,"id":{"name":"panic_unwind","disambiguator":[14218938340851961837,11099897245983054425]}},{"file_name":"/home/gautam/.cargo/registry/src/github.com-1ecc6299db9ec823/proc-macro-crate-0.1.4/src/lib.rs","num":15,"id":{"name":"toml","disambiguator":[15678776651944056456,16831117563282637211]}},{"file_name":"/home/gautam/.cargo/registry/src/github.com-1ecc6299db9ec823/proc-macro-crate-0.1.4/src/lib.rs","num":16,"id":{"name":"serde","disambiguator":[9038813648556765277,4167480622265422610]}},{"file_name":"/home/gautam/.cargo/registry/src/github.com-1ecc6299db9ec823/proc-macro-crate-0.1.4/src/lib.rs","num":17,"id":{"name":"serde_derive","disambiguator":[7405036298160419648,10191403185028390266]}}],"span":{"file_name":"/home/gautam/.cargo/registry/src/github.com-1ecc6299db9ec823/proc-macro-crate-0.1.4/src/lib.rs","byte_start":0,"byte_end":8414,"line_start":1,"line_end":274,"column_start":1,"column_end":2}},"imports":[],"defs":[{"kind":"Mod","id":{"krate":0,"index":0},"span":{"file_name":"/home/gautam/.cargo/registry/src/github.com-1ecc6299db9ec823/proc-macro-crate-0.1.4/src/lib.rs","byte_start":0,"byte_end":8414,"line_start":1,"line_end":274,"column_start":1,"column_end":2},"name":"","qualname":"::","value":"/home/gautam/.cargo/registry/src/github.com-1ecc6299db9ec823/proc-macro-crate-0.1.4/src/lib.rs","parent":null,"children":[{"krate":0,"index":10},{"krate":0,"index":11},{"krate":0,"index":12},{"krate":0,"index":21},{"krate":0,"index":24},{"krate":0,"index":25},{"krate":0,"index":27},{"krate":0,"index":28},{"krate":0,"index":32},{"krate":0,"index":33},{"krate":0,"index":41},{"krate":0,"index":44}],"decl_id":null,"docs":"[![](https://docs.rs/proc-macro-crate/badge.svg)](https://docs.rs/proc-macro-crate/) [![](https://img.shields.io/crates/v/proc-macro-crate.svg)](https://crates.io/crates/proc-macro-crate) [![](https://img.shields.io/crates/d/proc-macro-crate.png)](https://crates.io/crates/proc-macro-crate) [![Build Status](https://travis-ci.org/bkchr/proc-macro-crate.png?branch=master)](https://travis-ci.org/bkchr/proc-macro-crate)","sig":null,"attributes":[]},{"kind":"Function","id":{"krate":0,"index":25},"span":{"file_name":"/home/gautam/.cargo/registry/src/github.com-1ecc6299db9ec823/proc-macro-crate-0.1.4/src/lib.rs","byte_start":3003,"byte_end":3013,"line_start":82,"line_end":82,"column_start":8,"column_end":18},"name":"crate_name","qualname":"::crate_name","value":"fn (orig_name: &str) -> Result<String, String>","parent":null,"children":[],"decl_id":null,"docs":" Find the crate name for the given `orig_name` in the current `Cargo.toml`.","sig":null,"attributes":[]}],"impls":[],"refs":[],"macro_refs":[],"relations":[]}