{"config":{"output_file":null,"full_docs":false,"pub_only":true,"reachable_only":true,"distro_crate":false,"signatures":false,"borrow_data":false},"version":"0.19.0","compilation":{"directory":"/home/gautam/.cargo/registry/src/github.com-1ecc6299db9ec823/zeroize-0.9.3","program":"/home/gautam/.rustup/toolchains/stable-x86_64-unknown-linux-gnu/bin/rls","arguments":["--edition=2018","--crate-name","zeroize","/home/gautam/.cargo/registry/src/github.com-1ecc6299db9ec823/zeroize-0.9.3/src/lib.rs","--color","never","--crate-type","lib","--emit=dep-info,metadata","-C","debuginfo=2","--cfg","feature=\"alloc\"","--cfg","feature=\"default\"","--cfg","feature=\"std\"","--cfg","feature=\"zeroize_derive\"","-C","metadata=3ad5ef8fe1959b94","-C","extra-filename=-3ad5ef8fe1959b94","--out-dir","/home/gautam/code/substrate-tcr/target/rls/debug/deps","-L","dependency=/home/gautam/code/substrate-tcr/target/rls/debug/deps","--extern","zeroize_derive=/home/gautam/code/substrate-tcr/target/rls/debug/deps/libzeroize_derive-347200d8acbb330b.so","--cap-lints","allow","--error-format=json","--sysroot","/home/gautam/.rustup/toolchains/stable-x86_64-unknown-linux-gnu"],"output":"/home/gautam/code/substrate-tcr/target/rls/debug/deps/libzeroize-3ad5ef8fe1959b94.rmeta"},"prelude":{"crate_id":{"name":"zeroize","disambiguator":[600359687917707210,3215035039325411509]},"crate_root":"/home/gautam/.cargo/registry/src/github.com-1ecc6299db9ec823/zeroize-0.9.3/src","external_crates":[{"file_name":"/home/gautam/.cargo/registry/src/github.com-1ecc6299db9ec823/zeroize-0.9.3/src/lib.rs","num":1,"id":{"name":"core","disambiguator":[9113878364975505769,4626460723841361367]}},{"file_name":"/home/gautam/.cargo/registry/src/github.com-1ecc6299db9ec823/zeroize-0.9.3/src/lib.rs","num":2,"id":{"name":"compiler_builtins","disambiguator":[10636203250160794641,6979396832464280682]}},{"file_name":"/home/gautam/.cargo/registry/src/github.com-1ecc6299db9ec823/zeroize-0.9.3/src/lib.rs","num":3,"id":{"name":"rustc_std_workspace_core","disambiguator":[7259142600435629501,12221323364939802703]}},{"file_name":"/home/gautam/.cargo/registry/src/github.com-1ecc6299db9ec823/zeroize-0.9.3/src/lib.rs","num":4,"id":{"name":"std","disambiguator":[4418738106075590160,6298063093324017560]}},{"file_name":"/home/gautam/.cargo/registry/src/github.com-1ecc6299db9ec823/zeroize-0.9.3/src/lib.rs","num":5,"id":{"name":"alloc","disambiguator":[245280942947536957,12219005383890086938]}},{"file_name":"/home/gautam/.cargo/registry/src/github.com-1ecc6299db9ec823/zeroize-0.9.3/src/lib.rs","num":6,"id":{"name":"libc","disambiguator":[6161946279237914842,16521306710208745576]}},{"file_name":"/home/gautam/.cargo/registry/src/github.com-1ecc6299db9ec823/zeroize-0.9.3/src/lib.rs","num":7,"id":{"name":"unwind","disambiguator":[6542909105960794691,9677219093962929367]}},{"file_name":"/home/gautam/.cargo/registry/src/github.com-1ecc6299db9ec823/zeroize-0.9.3/src/lib.rs","num":8,"id":{"name":"cfg_if","disambiguator":[5468829561226316808,7834745881253856659]}},{"file_name":"/home/gautam/.cargo/registry/src/github.com-1ecc6299db9ec823/zeroize-0.9.3/src/lib.rs","num":9,"id":{"name":"hashbrown","disambiguator":[17700629721805382410,8884445337419759755]}},{"file_name":"/home/gautam/.cargo/registry/src/github.com-1ecc6299db9ec823/zeroize-0.9.3/src/lib.rs","num":10,"id":{"name":"rustc_std_workspace_alloc","disambiguator":[5673318663856259921,7992701887106127366]}},{"file_name":"/home/gautam/.cargo/registry/src/github.com-1ecc6299db9ec823/zeroize-0.9.3/src/lib.rs","num":11,"id":{"name":"backtrace","disambiguator":[14096840682646779984,4894716104918169263]}},{"file_name":"/home/gautam/.cargo/registry/src/github.com-1ecc6299db9ec823/zeroize-0.9.3/src/lib.rs","num":12,"id":{"name":"rustc_demangle","disambiguator":[17167590092810160364,15681868143498786567]}},{"file_name":"/home/gautam/.cargo/registry/src/github.com-1ecc6299db9ec823/zeroize-0.9.3/src/lib.rs","num":13,"id":{"name":"backtrace_sys","disambiguator":[9809686796458150241,12960706147778414440]}},{"file_name":"/home/gautam/.cargo/registry/src/github.com-1ecc6299db9ec823/zeroize-0.9.3/src/lib.rs","num":14,"id":{"name":"panic_unwind","disambiguator":[14218938340851961837,11099897245983054425]}},{"file_name":"/home/gautam/.cargo/registry/src/github.com-1ecc6299db9ec823/zeroize-0.9.3/src/lib.rs","num":15,"id":{"name":"zeroize_derive","disambiguator":[10394395909460917833,3958442503249985928]}}],"span":{"file_name":"/home/gautam/.cargo/registry/src/github.com-1ecc6299db9ec823/zeroize-0.9.3/src/lib.rs","byte_start":0,"byte_end":15362,"line_start":1,"line_end":479,"column_start":1,"column_end":2}},"imports":[{"kind":"GlobUse","ref_id":null,"span":{"file_name":"/home/gautam/.cargo/registry/src/github.com-1ecc6299db9ec823/zeroize-0.9.3/src/lib.rs","byte_start":9044,"byte_end":9045,"line_start":213,"line_end":213,"column_start":25,"column_end":26},"alias_span":null,"name":"*","value":"","parent":{"krate":0,"index":0}}],"defs":[{"kind":"Mod","id":{"krate":0,"index":0},"span":{"file_name":"/home/gautam/.cargo/registry/src/github.com-1ecc6299db9ec823/zeroize-0.9.3/src/lib.rs","byte_start":0,"byte_end":15362,"line_start":1,"line_end":479,"column_start":1,"column_end":2},"name":"","qualname":"::","value":"/home/gautam/.cargo/registry/src/github.com-1ecc6299db9ec823/zeroize-0.9.3/src/lib.rs","parent":null,"children":[{"krate":0,"index":10},{"krate":0,"index":11},{"krate":0,"index":12},{"krate":0,"index":13},{"krate":0,"index":14},{"krate":0,"index":15},{"krate":0,"index":16},{"krate":0,"index":21},{"krate":0,"index":24},{"krate":0,"index":26},{"krate":0,"index":27},{"krate":0,"index":30},{"krate":0,"index":72},{"krate":0,"index":73},{"krate":0,"index":74},{"krate":0,"index":75},{"krate":0,"index":76},{"krate":0,"index":77},{"krate":0,"index":78},{"krate":0,"index":79},{"krate":0,"index":80},{"krate":0,"index":81},{"krate":0,"index":82},{"krate":0,"index":83},{"krate":0,"index":84},{"krate":0,"index":85},{"krate":0,"index":86},{"krate":0,"index":87},{"krate":0,"index":31},{"krate":0,"index":88},{"krate":0,"index":92},{"krate":0,"index":96},{"krate":0,"index":100},{"krate":0,"index":104},{"krate":0,"index":108},{"krate":0,"index":112},{"krate":0,"index":116},{"krate":0,"index":120},{"krate":0,"index":124},{"krate":0,"index":128},{"krate":0,"index":132},{"krate":0,"index":136},{"krate":0,"index":140},{"krate":0,"index":144},{"krate":0,"index":148},{"krate":0,"index":152},{"krate":0,"index":156},{"krate":0,"index":160},{"krate":0,"index":164},{"krate":0,"index":168},{"krate":0,"index":172},{"krate":0,"index":176},{"krate":0,"index":180},{"krate":0,"index":184},{"krate":0,"index":188},{"krate":0,"index":192},{"krate":0,"index":196},{"krate":0,"index":200},{"krate":0,"index":204},{"krate":0,"index":208},{"krate":0,"index":212},{"krate":0,"index":216},{"krate":0,"index":220},{"krate":0,"index":224},{"krate":0,"index":228},{"krate":0,"index":232},{"krate":0,"index":236},{"krate":0,"index":240},{"krate":0,"index":244},{"krate":0,"index":248},{"krate":0,"index":252},{"krate":0,"index":256},{"krate":0,"index":260},{"krate":0,"index":264},{"krate":0,"index":268},{"krate":0,"index":272},{"krate":0,"index":276},{"krate":0,"index":280},{"krate":0,"index":284},{"krate":0,"index":288},{"krate":0,"index":292},{"krate":0,"index":296},{"krate":0,"index":300},{"krate":0,"index":304},{"krate":0,"index":308},{"krate":0,"index":312},{"krate":0,"index":316},{"krate":0,"index":320},{"krate":0,"index":324},{"krate":0,"index":328},{"krate":0,"index":332},{"krate":0,"index":336},{"krate":0,"index":340},{"krate":0,"index":32},{"krate":0,"index":36},{"krate":0,"index":39},{"krate":0,"index":42},{"krate":0,"index":45},{"krate":0,"index":47},{"krate":0,"index":51},{"krate":0,"index":54},{"krate":0,"index":58},{"krate":0,"index":61},{"krate":0,"index":64},{"krate":0,"index":67},{"krate":0,"index":68},{"krate":0,"index":70}],"decl_id":null,"docs":" Securely zero memory with a simple trait ([Zeroize]) built on stable Rust\n primitives which guarantee the operation will not be \"optimized away\".","sig":null,"attributes":[{"value":"no_std","span":{"file_name":"/home/gautam/.cargo/registry/src/github.com-1ecc6299db9ec823/zeroize-0.9.3/src/lib.rs","byte_start":8518,"byte_end":8528,"line_start":193,"line_end":193,"column_start":1,"column_end":11}},{"value":"deny(warnings, missing_docs, trivial_casts, unused_qualifications)","span":{"file_name":"/home/gautam/.cargo/registry/src/github.com-1ecc6299db9ec823/zeroize-0.9.3/src/lib.rs","byte_start":8529,"byte_end":8599,"line_start":194,"line_end":194,"column_start":1,"column_end":71}}]},{"kind":"Trait","id":{"krate":0,"index":24},"span":{"file_name":"/home/gautam/.cargo/registry/src/github.com-1ecc6299db9ec823/zeroize-0.9.3/src/lib.rs","byte_start":9314,"byte_end":9321,"line_start":223,"line_end":223,"column_start":11,"column_end":18},"name":"Zeroize","qualname":"::Zeroize","value":"Zeroize","parent":null,"children":[{"krate":0,"index":25}],"decl_id":null,"docs":" Trait for securely erasing types from memory\n","sig":null,"attributes":[]},{"kind":"Method","id":{"krate":0,"index":25},"span":{"file_name":"/home/gautam/.cargo/registry/src/github.com-1ecc6299db9ec823/zeroize-0.9.3/src/lib.rs","byte_start":9473,"byte_end":9480,"line_start":226,"line_end":226,"column_start":8,"column_end":15},"name":"zeroize","qualname":"::Zeroize::zeroize","value":"fn (&mut self) -> ()","parent":{"krate":0,"index":24},"children":[],"decl_id":null,"docs":" Zero out this object from memory (using Rust or OS intrinsics which\n ensure the zeroization operation is not \"optimized away\")\n","sig":null,"attributes":[]},{"kind":"Trait","id":{"krate":0,"index":26},"span":{"file_name":"/home/gautam/.cargo/registry/src/github.com-1ecc6299db9ec823/zeroize-0.9.3/src/lib.rs","byte_start":9583,"byte_end":9598,"line_start":230,"line_end":230,"column_start":11,"column_end":26},"name":"DefaultIsZeroes","qualname":"::DefaultIsZeroes","value":"DefaultIsZeroes: Copy + Default + Sized","parent":null,"children":[],"decl_id":null,"docs":" Marker trait for types whose `Default` is the desired zeroization result\n","sig":null,"attributes":[]},{"kind":"Struct","id":{"krate":0,"index":47},"span":{"file_name":"/home/gautam/.cargo/registry/src/github.com-1ecc6299db9ec823/zeroize-0.9.3/src/lib.rs","byte_start":12299,"byte_end":12308,"line_start":339,"line_end":339,"column_start":12,"column_end":21},"name":"Zeroizing","qualname":"::Zeroizing","value":"","parent":null,"children":[],"decl_id":null,"docs":" `Zeroizing` is a a wrapper for any `Z: Zeroize` type which implements a\n `Drop` handler which zeroizes dropped values.\n","sig":null,"attributes":[]},{"kind":"Method","id":{"krate":0,"index":53},"span":{"file_name":"/home/gautam/.cargo/registry/src/github.com-1ecc6299db9ec823/zeroize-0.9.3/src/lib.rs","byte_start":12451,"byte_end":12454,"line_start":346,"line_end":346,"column_start":12,"column_end":15},"name":"new","qualname":"<Zeroizing<Z>>::new","value":"fn (value: Z) -> Self","parent":null,"children":[],"decl_id":null,"docs":" Wrap a value in `Zeroizing`, ensuring it's zeroized on drop.\n","sig":null,"attributes":[]}],"impls":[{"id":0,"kind":"Direct","span":{"file_name":"/home/gautam/.cargo/registry/src/github.com-1ecc6299db9ec823/zeroize-0.9.3/src/lib.rs","byte_start":9647,"byte_end":9648,"line_start":232,"line_end":232,"column_start":21,"column_end":22},"value":"","parent":null,"children":[{"krate":0,"index":29}],"docs":"","sig":null,"attributes":[]},{"id":17,"kind":"Direct","span":{"file_name":"/home/gautam/.cargo/registry/src/github.com-1ecc6299db9ec823/zeroize-0.9.3/src/lib.rs","byte_start":10806,"byte_end":10813,"line_start":275,"line_end":275,"column_start":25,"column_end":32},"value":"","parent":null,"children":[{"krate":0,"index":35}],"docs":"","sig":null,"attributes":[]},{"id":18,"kind":"Direct","span":{"file_name":"/home/gautam/.cargo/registry/src/github.com-1ecc6299db9ec823/zeroize-0.9.3/src/lib.rs","byte_start":10967,"byte_end":10973,"line_start":286,"line_end":286,"column_start":21,"column_end":27},"value":"","parent":null,"children":[{"krate":0,"index":38}],"docs":"","sig":null,"attributes":[]},{"id":19,"kind":"Direct","span":{"file_name":"/home/gautam/.cargo/registry/src/github.com-1ecc6299db9ec823/zeroize-0.9.3/src/lib.rs","byte_start":11742,"byte_end":11745,"line_start":317,"line_end":317,"column_start":21,"column_end":24},"value":"","parent":null,"children":[{"krate":0,"index":44}],"docs":"","sig":null,"attributes":[]},{"id":20,"kind":"Direct","span":{"file_name":"/home/gautam/.cargo/registry/src/github.com-1ecc6299db9ec823/zeroize-0.9.3/src/lib.rs","byte_start":11980,"byte_end":11986,"line_start":329,"line_end":329,"column_start":18,"column_end":24},"value":"","parent":null,"children":[{"krate":0,"index":46}],"docs":"","sig":null,"attributes":[]},{"id":21,"kind":"Inherent","span":{"file_name":"/home/gautam/.cargo/registry/src/github.com-1ecc6299db9ec823/zeroize-0.9.3/src/lib.rs","byte_start":12334,"byte_end":12343,"line_start":341,"line_end":341,"column_start":9,"column_end":18},"value":"","parent":null,"children":[{"krate":0,"index":53}],"docs":"","sig":null,"attributes":[]},{"id":22,"kind":"Direct","span":{"file_name":"/home/gautam/.cargo/registry/src/github.com-1ecc6299db9ec823/zeroize-0.9.3/src/lib.rs","byte_start":12532,"byte_end":12541,"line_start":351,"line_end":351,"column_start":24,"column_end":33},"value":"","parent":null,"children":[{"krate":0,"index":56},{"krate":0,"index":57}],"docs":"","sig":null,"attributes":[]},{"id":23,"kind":"Direct","span":{"file_name":"/home/gautam/.cargo/registry/src/github.com-1ecc6299db9ec823/zeroize-0.9.3/src/lib.rs","byte_start":12670,"byte_end":12679,"line_start":362,"line_end":362,"column_start":27,"column_end":36},"value":"","parent":null,"children":[{"krate":0,"index":60}],"docs":"","sig":null,"attributes":[]},{"id":24,"kind":"Direct","span":{"file_name":"/home/gautam/.cargo/registry/src/github.com-1ecc6299db9ec823/zeroize-0.9.3/src/lib.rs","byte_start":12796,"byte_end":12805,"line_start":371,"line_end":371,"column_start":21,"column_end":30},"value":"","parent":null,"children":[{"krate":0,"index":63}],"docs":"","sig":null,"attributes":[]},{"id":25,"kind":"Direct","span":{"file_name":"/home/gautam/.cargo/registry/src/github.com-1ecc6299db9ec823/zeroize-0.9.3/src/lib.rs","byte_start":13081,"byte_end":13090,"line_start":383,"line_end":383,"column_start":18,"column_end":27},"value":"","parent":null,"children":[{"krate":0,"index":66}],"docs":"","sig":null,"attributes":[]}],"refs":[],"macro_refs":[],"relations":[{"span":{"file_name":"/home/gautam/.cargo/registry/src/github.com-1ecc6299db9ec823/zeroize-0.9.3/src/lib.rs","byte_start":9600,"byte_end":9604,"line_start":230,"line_end":230,"column_start":28,"column_end":32},"kind":"SuperTrait","from":{"krate":1,"index":1543},"to":{"krate":0,"index":26}},{"span":{"file_name":"/home/gautam/.cargo/registry/src/github.com-1ecc6299db9ec823/zeroize-0.9.3/src/lib.rs","byte_start":9607,"byte_end":9614,"line_start":230,"line_end":230,"column_start":35,"column_end":42},"kind":"SuperTrait","from":{"krate":1,"index":2189},"to":{"krate":0,"index":26}},{"span":{"file_name":"/home/gautam/.cargo/registry/src/github.com-1ecc6299db9ec823/zeroize-0.9.3/src/lib.rs","byte_start":9617,"byte_end":9622,"line_start":230,"line_end":230,"column_start":45,"column_end":50},"kind":"SuperTrait","from":{"krate":1,"index":1540},"to":{"krate":0,"index":26}},{"span":{"file_name":"/home/gautam/.cargo/registry/src/github.com-1ecc6299db9ec823/zeroize-0.9.3/src/lib.rs","byte_start":9647,"byte_end":9648,"line_start":232,"line_end":232,"column_start":21,"column_end":22},"kind":{"Impl":{"id":0}},"from":{"krate":0,"index":28},"to":{"krate":0,"index":24}},{"span":{"file_name":"/home/gautam/.cargo/registry/src/github.com-1ecc6299db9ec823/zeroize-0.9.3/src/lib.rs","byte_start":10806,"byte_end":10813,"line_start":275,"line_end":275,"column_start":25,"column_end":32},"kind":{"Impl":{"id":17}},"from":{"krate":1,"index":5620},"to":{"krate":0,"index":24}},{"span":{"file_name":"/home/gautam/.cargo/registry/src/github.com-1ecc6299db9ec823/zeroize-0.9.3/src/lib.rs","byte_start":10967,"byte_end":10973,"line_start":286,"line_end":286,"column_start":21,"column_end":27},"kind":{"Impl":{"id":18}},"from":{"krate":1,"index":28500},"to":{"krate":0,"index":24}},{"span":{"file_name":"/home/gautam/.cargo/registry/src/github.com-1ecc6299db9ec823/zeroize-0.9.3/src/lib.rs","byte_start":11742,"byte_end":11745,"line_start":317,"line_end":317,"column_start":21,"column_end":24},"kind":{"Impl":{"id":19}},"from":{"krate":5,"index":3718},"to":{"krate":0,"index":24}},{"span":{"file_name":"/home/gautam/.cargo/registry/src/github.com-1ecc6299db9ec823/zeroize-0.9.3/src/lib.rs","byte_start":11980,"byte_end":11986,"line_start":329,"line_end":329,"column_start":18,"column_end":24},"kind":{"Impl":{"id":20}},"from":{"krate":5,"index":4279},"to":{"krate":0,"index":24}},{"span":{"file_name":"/home/gautam/.cargo/registry/src/github.com-1ecc6299db9ec823/zeroize-0.9.3/src/lib.rs","byte_start":12334,"byte_end":12343,"line_start":341,"line_end":341,"column_start":9,"column_end":18},"kind":{"Impl":{"id":21}},"from":{"krate":0,"index":47},"to":{"krate":4294967295,"index":4294967295}},{"span":{"file_name":"/home/gautam/.cargo/registry/src/github.com-1ecc6299db9ec823/zeroize-0.9.3/src/lib.rs","byte_start":12532,"byte_end":12541,"line_start":351,"line_end":351,"column_start":24,"column_end":33},"kind":{"Impl":{"id":22}},"from":{"krate":0,"index":47},"to":{"krate":1,"index":1704}},{"span":{"file_name":"/home/gautam/.cargo/registry/src/github.com-1ecc6299db9ec823/zeroize-0.9.3/src/lib.rs","byte_start":12670,"byte_end":12679,"line_start":362,"line_end":362,"column_start":27,"column_end":36},"kind":{"Impl":{"id":23}},"from":{"krate":0,"index":47},"to":{"krate":1,"index":1715}},{"span":{"file_name":"/home/gautam/.cargo/registry/src/github.com-1ecc6299db9ec823/zeroize-0.9.3/src/lib.rs","byte_start":12796,"byte_end":12805,"line_start":371,"line_end":371,"column_start":21,"column_end":30},"kind":{"Impl":{"id":24}},"from":{"krate":0,"index":47},"to":{"krate":0,"index":24}},{"span":{"file_name":"/home/gautam/.cargo/registry/src/github.com-1ecc6299db9ec823/zeroize-0.9.3/src/lib.rs","byte_start":13081,"byte_end":13090,"line_start":383,"line_end":383,"column_start":18,"column_end":27},"kind":{"Impl":{"id":25}},"from":{"krate":0,"index":47},"to":{"krate":1,"index":1726}}]}